geodezyx/__init__.py
geodezyx/athmo/__init__.py
geodezyx/athmo/athmo.py
geodezyx/athmo/vmf1_compute.py
geodezyx/conv/__init__.py
geodezyx/conv/conv_angle.py
geodezyx/conv/conv_constant.py
geodezyx/conv/conv_coords.py
geodezyx/conv/conv_geometric.py
geodezyx/conv/conv_proj_lambert.py
geodezyx/conv/conv_proj_utm.py
geodezyx/conv/conv_rinex.py
geodezyx/conv/conv_rotation_matrices.py
geodezyx/conv/conv_time.py
geodezyx/externlib/__init__.py
geodezyx/externlib/externlib.py
geodezyx/files_rw/__init__.py
geodezyx/files_rw/geo_files_converter_lib.py
geodezyx/files_rw/read_antex.py
geodezyx/files_rw/read_athmo.py
geodezyx/files_rw/read_coords_misc.py
geodezyx/files_rw/read_coords_time_series.py
geodezyx/files_rw/read_eop.py
geodezyx/files_rw/read_geo_files_misc.py
geodezyx/files_rw/read_gnss_prods.py
geodezyx/files_rw/read_gnss_qc.py
geodezyx/files_rw/read_igs_combi.py
geodezyx/files_rw/read_logsheets.py
geodezyx/files_rw/read_rinex.py
geodezyx/files_rw/read_rinex_nav.py
geodezyx/files_rw/read_sinex.py
geodezyx/files_rw/read_slr.py
geodezyx/files_rw/write_geo_files.py
geodezyx/files_rw/write_rinex.py
geodezyx/files_rw/write_tropo_spotgins.py
geodezyx/geodyn/__init__.py
geodezyx/geodyn/emsgfz_load_interp.py
geodezyx/geodyn/euler_pole_calc.py
geodezyx/geodyn/velo_field_map_plt.py
geodezyx/geodyn/volcano_mogi.py
geodezyx/gnss_edu/__init__.py
geodezyx/gnss_edu/compute_vmf1_values.py
geodezyx/gnss_edu/download_VMF.py
geodezyx/gnss_edu/gmf_function.py
geodezyx/gnss_edu/gnss_edu.py
geodezyx/gnss_edu/gnss_edu_test_skyplot.py
geodezyx/gnss_edu/gpt3.py
geodezyx/gnss_edu/klobuchar.py
geodezyx/gnss_edu/read_vmf1_grid.py
geodezyx/gnss_edu/vmf1_ht.py
geodezyx/interp/__init__.py
geodezyx/interp/interp.py
geodezyx/logconfig/__init__.py
geodezyx/logconfig/loggzyx.py
geodezyx/marine/__init__.py
geodezyx/marine/dac.py
geodezyx/marine/marine.py
geodezyx/marine/obp.py
geodezyx/marine/obscom.py
geodezyx/marine/netcdf_a0a/a0a_read.py
geodezyx/marine/netcdf_a0a/netcdf_make_work01a.py
geodezyx-5.0.1.dist-info/licenses/LICENSE
geodezyx-5.0.1.dist-info/METADATA
geodezyx-5.0.1.dist-info/WHEEL
geodezyx-5.0.1.dist-info/entry_points.txt
geodezyx-5.0.1.dist-info/top_level.txt
geodezyx-5.0.1.dist-info/RECORD
