Metadata-Version: 2.4
Name: geodezyx
Version: 5.0.1
Summary: geodezyx (a.k.a. The GeodeZYX toolbox) aims to provide simple but useful functions for Geodesy and Geophysics.
Author-email: Pierre Sakic <sakic@ipgp.fr>, Gustavo Mansur <mansur@gfz-potsdam.de>
License-Expression: LGPL-3.0-or-later
Project-URL: Homepage, https://github.com/IPGP/geodezyx
Keywords: geodesy,geophysics,reference frames,gnss
Classifier: Development Status :: 3 - Alpha
Classifier: Development Status :: 4 - Beta
Classifier: Intended Audience :: Science/Research
Classifier: Programming Language :: Python :: 3
Classifier: Programming Language :: Python :: 3.9
Classifier: Programming Language :: Python :: 3.10
Classifier: Programming Language :: Python :: 3.11
Classifier: Programming Language :: Python :: 3.12
Classifier: Programming Language :: Python :: 3.13
Classifier: Programming Language :: Python :: 3 :: Only
Requires-Python: <4,>=3.5
License-File: LICENSE
Requires-Dist: chardet
Requires-Dist: colorlog
Requires-Dist: hatanaka
Requires-Dist: natsort
Requires-Dist: matplotlib
Requires-Dist: numpy
Requires-Dist: pyyaml
Requires-Dist: pathvalidate
Requires-Dist: pandas
Requires-Dist: scipy
Requires-Dist: sympy
Requires-Dist: tabulate
Requires-Dist: tqdm
Requires-Dist: vincenty
Requires-Dist: wheel
Requires-Dist: xarray
Requires-Dist: logging_tree
Requires-Dist: mergedeep
Provides-Extra: full
Requires-Dist: netCDF4; extra == "full"
Requires-Dist: kepler.py; extra == "full"
Requires-Dist: ncompress; extra == "full"
Requires-Dist: seawater; extra == "full"
Requires-Dist: gsw; extra == "full"
Requires-Dist: pyorbital; extra == "full"
Requires-Dist: pytwobodyorbit; extra == "full"
Provides-Extra: edu
Requires-Dist: gnsstoolbox; extra == "edu"
Requires-Dist: gpsdatetime; extra == "edu"
Requires-Dist: seaborn; extra == "edu"
Requires-Dist: plotly; extra == "edu"
Dynamic: license-file
